{
    "20250403042956": {
        "throughput": 1327.0,
        "packets_lost": 1.2,
        "packet_loss_rate": 3.22,
        "jitter": 17.591,
        "speed": 51.0
    },
    "20250403042958": {
        "throughput": 687.3,
        "packets_lost": 2.3,
        "packet_loss_rate": 1.55,
        "jitter": 21.647,
        "speed": 33.0
    },
    "20250403043000": {
        "throughput": 1518.0,
        "packets_lost": 2.1,
        "packet_loss_rate": 1.6,
        "jitter": 24.696,
        "speed": 5.0
    },
    "20250403043002": {
        "throughput": 1012.1,
        "packets_lost": 0.9,
        "packet_loss_rate": 0.81,
        "jitter": 24.234,
        "speed": 34.0
    },
    "20250403043004": {
        "throughput": 1011.6,
        "packets_lost": 1.4,
        "packet_loss_rate": 3.44,
        "jitter": 24.024,
        "speed": 39.0
    },
    "QoE": 85.4698738,
    "timestamp": 20250403043004
}