{
    "20250410232006": {
        "throughput": 1427.4,
        "packets_lost": 4.3,
        "packet_loss_rate": 3.72,
        "jitter": 25.965,
        "speed": 23.0
    },
    "20250410232008": {
        "throughput": 779.5,
        "packets_lost": 4.1,
        "packet_loss_rate": 0.93,
        "jitter": 23.272,
        "speed": 25.0
    },
    "20250410232010": {
        "throughput": 778.1,
        "packets_lost": 0.3,
        "packet_loss_rate": 2.66,
        "jitter": 22.601,
        "speed": 16.0
    },
    "20250410232012": {
        "throughput": 957.7,
        "packets_lost": 1.5,
        "packet_loss_rate": 1.0,
        "jitter": 21.031,
        "speed": 33.0
    },
    "20250410232014": {
        "throughput": 1063.6,
        "packets_lost": 4.7,
        "packet_loss_rate": 3.91,
        "jitter": 25.289,
        "speed": 15.0
    },
    "QoE": 83.24856200000002,
    "timestamp": 20250410232014
}