{
    "20250406053646": {
        "throughput": 1271.1,
        "packets_lost": 1.3,
        "packet_loss_rate": 3.63,
        "jitter": 26.27,
        "speed": 42.0
    },
    "20250406053648": {
        "throughput": 1259.5,
        "packets_lost": 1.0,
        "packet_loss_rate": 1.88,
        "jitter": 24.837,
        "speed": 28.0
    },
    "20250406053650": {
        "throughput": 893.5,
        "packets_lost": 1.7,
        "packet_loss_rate": 1.59,
        "jitter": 16.983,
        "speed": 21.0
    },
    "20250406053652": {
        "throughput": 755.8,
        "packets_lost": 1.9,
        "packet_loss_rate": 2.83,
        "jitter": 21.766,
        "speed": 38.0
    },
    "20250406053654": {
        "throughput": 746.6,
        "packets_lost": 3.0,
        "packet_loss_rate": 1.63,
        "jitter": 21.725,
        "speed": 10.0
    },
    "QoE": 84.22241900000002,
    "timestamp": 20250406053654
}