{
    "20250413020856": {
        "throughput": 1495.1,
        "packets_lost": 5.0,
        "packet_loss_rate": 1.19,
        "jitter": 15.674,
        "speed": 44.0
    },
    "20250413020858": {
        "throughput": 844.1,
        "packets_lost": 2.7,
        "packet_loss_rate": 2.43,
        "jitter": 21.513,
        "speed": 3.0
    },
    "20250413020900": {
        "throughput": 1239.2,
        "packets_lost": 1.6,
        "packet_loss_rate": 2.16,
        "jitter": 28.649,
        "speed": 24.0
    },
    "20250413020902": {
        "throughput": 814.5,
        "packets_lost": 3.8,
        "packet_loss_rate": 0.64,
        "jitter": 29.085,
        "speed": 43.0
    },
    "20250413020904": {
        "throughput": 835.6,
        "packets_lost": 1.8,
        "packet_loss_rate": 3.29,
        "jitter": 17.975,
        "speed": 56.0
    },
    "QoE": 85.4922974,
    "timestamp": 20250413020904
}