{
    "20250403093326": {
        "throughput": 1319.8,
        "packets_lost": 0.5,
        "packet_loss_rate": 1.52,
        "jitter": 27.08085558556779,
        "speed": 26.0
    },
    "20250403093328": {
        "throughput": 759.5,
        "packets_lost": 0.8,
        "packet_loss_rate": 0.24,
        "jitter": 25.968069587583006,
        "speed": 13.0
    },
    "20250403093330": {
        "throughput": 1301.5,
        "packets_lost": 2.7,
        "packet_loss_rate": 0.88,
        "jitter": 30.201894211078816,
        "speed": 52.0
    },
    "20250403093332": {
        "throughput": 1023.3,
        "packets_lost": 4.0,
        "packet_loss_rate": 1.37,
        "jitter": 26.742253263392385,
        "speed": 24.0
    },
    "20250403093334": {
        "throughput": 1569.9,
        "packets_lost": 1.6,
        "packet_loss_rate": 0.02,
        "jitter": 21.38901821800701,
        "speed": 20.0
    },
    "QoE": 85.98109200000002,
    "timestamp": 20250403093334
}