{
    "20250404184016": {
        "throughput": 1529.4,
        "packets_lost": 0.0,
        "packet_loss_rate": 2.54,
        "jitter": 24.729202789762525,
        "speed": 17.0
    },
    "20250404184018": {
        "throughput": 1524.0,
        "packets_lost": 3.5,
        "packet_loss_rate": 2.94,
        "jitter": 15.681596535454545,
        "speed": 41.0
    },
    "20250404184020": {
        "throughput": 690.1,
        "packets_lost": 2.6,
        "packet_loss_rate": 2.71,
        "jitter": 26.349938072224624,
        "speed": 7.0
    },
    "20250404184022": {
        "throughput": 1455.8,
        "packets_lost": 3.0,
        "packet_loss_rate": 1.38,
        "jitter": 28.71703560022862,
        "speed": 1.0
    },
    "20250404184024": {
        "throughput": 1245.2,
        "packets_lost": 1.0,
        "packet_loss_rate": 4.49,
        "jitter": 27.024088285472892,
        "speed": 34.0
    },
    "QoE": 78.8958088,
    "timestamp": 20250404184024
}