{
    "20250409115756": {
        "throughput": 1492.8,
        "packets_lost": 3.6,
        "packet_loss_rate": 1.31,
        "jitter": 27.562,
        "speed": 10.0
    },
    "20250409115758": {
        "throughput": 1137.2,
        "packets_lost": 4.1,
        "packet_loss_rate": 0.36,
        "jitter": 17.776,
        "speed": 42.0
    },
    "20250409115800": {
        "throughput": 970.3,
        "packets_lost": 3.8,
        "packet_loss_rate": 3.43,
        "jitter": 17.874,
        "speed": 8.0
    },
    "20250409115802": {
        "throughput": 1063.3,
        "packets_lost": 3.1,
        "packet_loss_rate": 4.76,
        "jitter": 17.917,
        "speed": 50.0
    },
    "20250409115804": {
        "throughput": 1019.7,
        "packets_lost": 3.4,
        "packet_loss_rate": 3.53,
        "jitter": 26.446,
        "speed": 40.0
    },
    "QoE": 83.17441260000001,
    "timestamp": 20250409115804
}