{
    "20250403193936": {
        "throughput": 755.4,
        "packets_lost": 1.5,
        "packet_loss_rate": 2.04,
        "jitter": 17.650021711703296,
        "speed": 46.0
    },
    "20250403193938": {
        "throughput": 1130.8,
        "packets_lost": 0.6,
        "packet_loss_rate": 2.66,
        "jitter": 27.68717954947569,
        "speed": 47.0
    },
    "20250403193940": {
        "throughput": 694.1,
        "packets_lost": 2.7,
        "packet_loss_rate": 2.87,
        "jitter": 16.767201212778833,
        "speed": 48.0
    },
    "20250403193942": {
        "throughput": 1322.0,
        "packets_lost": 4.1,
        "packet_loss_rate": 1.38,
        "jitter": 23.955609072045938,
        "speed": 51.0
    },
    "20250403193944": {
        "throughput": 1253.9,
        "packets_lost": 1.9,
        "packet_loss_rate": 4.9,
        "jitter": 28.33143131015991,
        "speed": 5.0
    },
    "QoE": 76.642281,
    "timestamp": 20250403193944
}