{
    "20250407043306": {
        "throughput": 1044.9,
        "packets_lost": 2.2,
        "packet_loss_rate": 1.94,
        "jitter": 26.401,
        "speed": 16.0
    },
    "20250407043308": {
        "throughput": 1588.6,
        "packets_lost": 2.3,
        "packet_loss_rate": 1.66,
        "jitter": 23.136,
        "speed": 1.0
    },
    "20250407043310": {
        "throughput": 1580.5,
        "packets_lost": 1.6,
        "packet_loss_rate": 0.67,
        "jitter": 15.554,
        "speed": 32.0
    },
    "20250407043312": {
        "throughput": 620.2,
        "packets_lost": 4.0,
        "packet_loss_rate": 3.07,
        "jitter": 22.928,
        "speed": 11.0
    },
    "20250407043314": {
        "throughput": 1269.5,
        "packets_lost": 1.3,
        "packet_loss_rate": 4.7,
        "jitter": 16.673,
        "speed": 59.0
    },
    "QoE": 85.23883219999999,
    "timestamp": 20250407043314
}