{
    "20250410182646": {
        "throughput": 1587.7,
        "packets_lost": 1.7,
        "packet_loss_rate": 3.56,
        "jitter": 28.769682390200273,
        "speed": 35.0
    },
    "20250410182648": {
        "throughput": 1495.0,
        "packets_lost": 0.8,
        "packet_loss_rate": 3.8,
        "jitter": 23.27079934557017,
        "speed": 49.0
    },
    "20250410182650": {
        "throughput": 967.9,
        "packets_lost": 0.6,
        "packet_loss_rate": 4.6,
        "jitter": 32.19195317498808,
        "speed": 37.0
    },
    "20250410182652": {
        "throughput": 1120.9,
        "packets_lost": 2.7,
        "packet_loss_rate": 2.39,
        "jitter": 19.172942253752293,
        "speed": 8.0
    },
    "20250410182654": {
        "throughput": 1499.1,
        "packets_lost": 0.6,
        "packet_loss_rate": 1.31,
        "jitter": 24.26440641584253,
        "speed": 20.0
    },
    "QoE": 76.8427386,
    "timestamp": 20250410182654
}