{
    "20250408124356": {
        "throughput": 1456.4,
        "packets_lost": 1.7,
        "packet_loss_rate": 2.21,
        "jitter": 22.451,
        "speed": 19.0
    },
    "20250408124358": {
        "throughput": 1494.3,
        "packets_lost": 3.1,
        "packet_loss_rate": 4.69,
        "jitter": 28.998,
        "speed": 9.0
    },
    "20250408124400": {
        "throughput": 1596.8,
        "packets_lost": 3.1,
        "packet_loss_rate": 1.35,
        "jitter": 17.735,
        "speed": 6.0
    },
    "20250408124402": {
        "throughput": 1280.3,
        "packets_lost": 0.9,
        "packet_loss_rate": 1.17,
        "jitter": 28.55,
        "speed": 31.0
    },
    "20250408124404": {
        "throughput": 1487.6,
        "packets_lost": 3.0,
        "packet_loss_rate": 3.64,
        "jitter": 27.735,
        "speed": 45.0
    },
    "QoE": 85.36725979999999,
    "timestamp": 20250408124404
}