{
    "20250410230036": {
        "throughput": 1162.1,
        "packets_lost": 4.6,
        "packet_loss_rate": 0.9,
        "jitter": 17.79,
        "speed": 41.0
    },
    "20250410230038": {
        "throughput": 1528.9,
        "packets_lost": 4.7,
        "packet_loss_rate": 4.42,
        "jitter": 25.362,
        "speed": 5.0
    },
    "20250410230040": {
        "throughput": 1443.7,
        "packets_lost": 3.5,
        "packet_loss_rate": 3.88,
        "jitter": 17.383,
        "speed": 52.0
    },
    "20250410230042": {
        "throughput": 1571.3,
        "packets_lost": 4.8,
        "packet_loss_rate": 1.89,
        "jitter": 21.225,
        "speed": 39.0
    },
    "20250410230044": {
        "throughput": 752.4,
        "packets_lost": 2.6,
        "packet_loss_rate": 1.78,
        "jitter": 25.067,
        "speed": 16.0
    },
    "QoE": 84.7962226,
    "timestamp": 20250410230044
}