{
    "20250403131426": {
        "throughput": 1106.7,
        "packets_lost": 1.9,
        "packet_loss_rate": 2.66,
        "jitter": 15.279,
        "speed": 22.0
    },
    "20250403131428": {
        "throughput": 1551.8,
        "packets_lost": 0.0,
        "packet_loss_rate": 0.35,
        "jitter": 25.394,
        "speed": 54.0
    },
    "20250403131430": {
        "throughput": 1142.0,
        "packets_lost": 5.0,
        "packet_loss_rate": 2.0,
        "jitter": 25.662,
        "speed": 38.0
    },
    "20250403131432": {
        "throughput": 1350.8,
        "packets_lost": 2.8,
        "packet_loss_rate": 3.64,
        "jitter": 20.195,
        "speed": 36.0
    },
    "20250403131434": {
        "throughput": 638.2,
        "packets_lost": 0.4,
        "packet_loss_rate": 2.49,
        "jitter": 15.219,
        "speed": 43.0
    },
    "QoE": 84.88193079999999,
    "timestamp": 20250403131434
}