{
    "20250408235206": {
        "throughput": 860.4,
        "packets_lost": 1.8,
        "packet_loss_rate": 0.31,
        "jitter": 26.884,
        "speed": 47.0
    },
    "20250408235208": {
        "throughput": 1193.4,
        "packets_lost": 2.6,
        "packet_loss_rate": 4.33,
        "jitter": 23.125,
        "speed": 3.0
    },
    "20250408235210": {
        "throughput": 652.1,
        "packets_lost": 3.5,
        "packet_loss_rate": 0.47,
        "jitter": 29.552,
        "speed": 25.0
    },
    "20250408235212": {
        "throughput": 939.8,
        "packets_lost": 2.8,
        "packet_loss_rate": 4.73,
        "jitter": 17.389,
        "speed": 2.0
    },
    "20250408235214": {
        "throughput": 964.0,
        "packets_lost": 3.3,
        "packet_loss_rate": 2.55,
        "jitter": 21.915,
        "speed": 27.0
    },
    "QoE": 83.2618974,
    "timestamp": 20250408235214
}