{
    "20250409122656": {
        "throughput": 1113.0,
        "packets_lost": 3.3,
        "packet_loss_rate": 2.81,
        "jitter": 26.077,
        "speed": 59.0
    },
    "20250409122658": {
        "throughput": 710.9,
        "packets_lost": 4.6,
        "packet_loss_rate": 1.23,
        "jitter": 21.944,
        "speed": 38.0
    },
    "20250409122700": {
        "throughput": 1552.4,
        "packets_lost": 1.6,
        "packet_loss_rate": 3.85,
        "jitter": 18.048,
        "speed": 9.0
    },
    "20250409122702": {
        "throughput": 661.0,
        "packets_lost": 3.3,
        "packet_loss_rate": 3.86,
        "jitter": 19.491,
        "speed": 9.0
    },
    "20250409122704": {
        "throughput": 968.9,
        "packets_lost": 4.7,
        "packet_loss_rate": 3.17,
        "jitter": 18.54,
        "speed": 33.0
    },
    "QoE": 81.7074288,
    "timestamp": 20250409122704
}