{
    "20250403134226": {
        "throughput": 1421.8,
        "packets_lost": 4.2,
        "packet_loss_rate": 3.61,
        "jitter": 18.785,
        "speed": 51.0
    },
    "20250403134228": {
        "throughput": 808.1,
        "packets_lost": 0.8,
        "packet_loss_rate": 0.2,
        "jitter": 24.091,
        "speed": 42.0
    },
    "20250403134230": {
        "throughput": 656.7,
        "packets_lost": 4.2,
        "packet_loss_rate": 1.18,
        "jitter": 19.436,
        "speed": 52.0
    },
    "20250403134232": {
        "throughput": 1586.2,
        "packets_lost": 0.1,
        "packet_loss_rate": 2.15,
        "jitter": 19.509,
        "speed": 50.0
    },
    "20250403134234": {
        "throughput": 731.9,
        "packets_lost": 2.3,
        "packet_loss_rate": 3.23,
        "jitter": 28.745,
        "speed": 21.0
    },
    "QoE": 84.51181260000001,
    "timestamp": 20250403134234
}