{
    "20250404025056": {
        "throughput": 796.3,
        "packets_lost": 2.4,
        "packet_loss_rate": 3.32,
        "jitter": 19.299,
        "speed": 45.0
    },
    "20250404025058": {
        "throughput": 1480.6,
        "packets_lost": 3.0,
        "packet_loss_rate": 3.91,
        "jitter": 17.311,
        "speed": 51.0
    },
    "20250404025100": {
        "throughput": 1257.7,
        "packets_lost": 3.7,
        "packet_loss_rate": 2.97,
        "jitter": 22.198,
        "speed": 21.0
    },
    "20250404025102": {
        "throughput": 1315.8,
        "packets_lost": 1.1,
        "packet_loss_rate": 1.88,
        "jitter": 24.731,
        "speed": 11.0
    },
    "20250404025104": {
        "throughput": 1375.8,
        "packets_lost": 2.7,
        "packet_loss_rate": 2.2,
        "jitter": 18.367,
        "speed": 20.0
    },
    "QoE": 82.9603728,
    "timestamp": 20250404025104
}