{
    "20250413205846": {
        "throughput": 977.0,
        "packets_lost": 1.2,
        "packet_loss_rate": 0.17,
        "jitter": 15.117,
        "speed": 59.0
    },
    "20250413205848": {
        "throughput": 1429.5,
        "packets_lost": 1.2,
        "packet_loss_rate": 3.3,
        "jitter": 23.421,
        "speed": 47.0
    },
    "20250413205850": {
        "throughput": 1143.6,
        "packets_lost": 3.0,
        "packet_loss_rate": 3.22,
        "jitter": 17.429,
        "speed": 23.0
    },
    "20250413205852": {
        "throughput": 1149.5,
        "packets_lost": 3.8,
        "packet_loss_rate": 1.36,
        "jitter": 19.165,
        "speed": 29.0
    },
    "20250413205854": {
        "throughput": 1188.9,
        "packets_lost": 2.7,
        "packet_loss_rate": 1.81,
        "jitter": 18.916,
        "speed": 21.0
    },
    "QoE": 85.9306218,
    "timestamp": 20250413205854
}