{
    "20250406000416": {
        "throughput": 1259.9,
        "packets_lost": 4.1,
        "packet_loss_rate": 2.81,
        "jitter": 24.287,
        "speed": 30.0
    },
    "20250406000418": {
        "throughput": 993.4,
        "packets_lost": 1.1,
        "packet_loss_rate": 3.79,
        "jitter": 21.604,
        "speed": 10.0
    },
    "20250406000420": {
        "throughput": 1486.5,
        "packets_lost": 3.6,
        "packet_loss_rate": 1.47,
        "jitter": 27.232,
        "speed": 54.0
    },
    "20250406000422": {
        "throughput": 1025.2,
        "packets_lost": 2.5,
        "packet_loss_rate": 3.29,
        "jitter": 15.511,
        "speed": 35.0
    },
    "20250406000424": {
        "throughput": 1106.5,
        "packets_lost": 3.4,
        "packet_loss_rate": 1.93,
        "jitter": 18.402,
        "speed": 36.0
    },
    "QoE": 82.9253368,
    "timestamp": 20250406000424
}