{
    "20250414013536": {
        "throughput": 756.6,
        "packets_lost": 2.9,
        "packet_loss_rate": 2.87,
        "jitter": 19.381,
        "speed": 30.0
    },
    "20250414013538": {
        "throughput": 1139.4,
        "packets_lost": 5.0,
        "packet_loss_rate": 1.46,
        "jitter": 18.704,
        "speed": 51.0
    },
    "20250414013540": {
        "throughput": 1495.6,
        "packets_lost": 2.7,
        "packet_loss_rate": 1.21,
        "jitter": 23.324,
        "speed": 14.0
    },
    "20250414013542": {
        "throughput": 1412.1,
        "packets_lost": 2.7,
        "packet_loss_rate": 2.5,
        "jitter": 16.152,
        "speed": 51.0
    },
    "20250414013544": {
        "throughput": 1107.2,
        "packets_lost": 1.0,
        "packet_loss_rate": 2.93,
        "jitter": 16.499,
        "speed": 37.0
    },
    "QoE": 85.80003260000001,
    "timestamp": 20250414013544
}