{
    "20250414010936": {
        "throughput": 960.3,
        "packets_lost": 2.7,
        "packet_loss_rate": 2.31,
        "jitter": 22.987,
        "speed": 53.0
    },
    "20250414010938": {
        "throughput": 1397.7,
        "packets_lost": 0.0,
        "packet_loss_rate": 2.87,
        "jitter": 26.917,
        "speed": 54.0
    },
    "20250414010940": {
        "throughput": 955.7,
        "packets_lost": 4.7,
        "packet_loss_rate": 2.06,
        "jitter": 23.004,
        "speed": 31.0
    },
    "20250414010942": {
        "throughput": 1429.0,
        "packets_lost": 4.7,
        "packet_loss_rate": 4.99,
        "jitter": 18.15,
        "speed": 5.0
    },
    "20250414010944": {
        "throughput": 1231.5,
        "packets_lost": 1.9,
        "packet_loss_rate": 3.03,
        "jitter": 24.349,
        "speed": 46.0
    },
    "QoE": 81.7490278,
    "timestamp": 20250414010944
}