{
    "20250411073756": {
        "throughput": 1503.3,
        "packets_lost": 4.0,
        "packet_loss_rate": 1.52,
        "jitter": 22.612809851886936,
        "speed": 37.0
    },
    "20250411073758": {
        "throughput": 767.7,
        "packets_lost": 3.6,
        "packet_loss_rate": 1.62,
        "jitter": 19.23757965896523,
        "speed": 2.0
    },
    "20250411073800": {
        "throughput": 955.7,
        "packets_lost": 2.6,
        "packet_loss_rate": 2.45,
        "jitter": 26.288751620180715,
        "speed": 53.0
    },
    "20250411073802": {
        "throughput": 803.6,
        "packets_lost": 1.5,
        "packet_loss_rate": 4.21,
        "jitter": 26.889198293244124,
        "speed": 24.0
    },
    "20250411073804": {
        "throughput": 600.3,
        "packets_lost": 0.1,
        "packet_loss_rate": 0.31,
        "jitter": 28.461182008327665,
        "speed": 50.0
    },
    "QoE": 78.9873418,
    "timestamp": 20250411073804
}