{
    "20250405094526": {
        "throughput": 852.8,
        "packets_lost": 0.8,
        "packet_loss_rate": 2.66,
        "jitter": 17.06289913535649,
        "speed": 18.0
    },
    "20250405094528": {
        "throughput": 827.2,
        "packets_lost": 0.4,
        "packet_loss_rate": 2.33,
        "jitter": 24.98898786923258,
        "speed": 6.0
    },
    "20250405094530": {
        "throughput": 1002.3,
        "packets_lost": 3.6,
        "packet_loss_rate": 0.12,
        "jitter": 28.976286612740623,
        "speed": 40.0
    },
    "20250405094532": {
        "throughput": 1324.6,
        "packets_lost": 3.6,
        "packet_loss_rate": 3.05,
        "jitter": 27.49173032160664,
        "speed": 43.0
    },
    "20250405094534": {
        "throughput": 1218.1,
        "packets_lost": 2.7,
        "packet_loss_rate": 4.13,
        "jitter": 33.86708162699561,
        "speed": 16.0
    },
    "QoE": 78.89778340000001,
    "timestamp": 20250405094534
}