{
    "20250406122756": {
        "throughput": 1030.4,
        "packets_lost": 3.2,
        "packet_loss_rate": 1.57,
        "jitter": 23.166,
        "speed": 13.0
    },
    "20250406122758": {
        "throughput": 1484.2,
        "packets_lost": 1.1,
        "packet_loss_rate": 1.67,
        "jitter": 19.876,
        "speed": 27.0
    },
    "20250406122800": {
        "throughput": 1362.2,
        "packets_lost": 1.4,
        "packet_loss_rate": 0.85,
        "jitter": 28.904,
        "speed": 8.0
    },
    "20250406122802": {
        "throughput": 1220.3,
        "packets_lost": 3.4,
        "packet_loss_rate": 0.58,
        "jitter": 22.221,
        "speed": 48.0
    },
    "20250406122804": {
        "throughput": 1418.7,
        "packets_lost": 2.5,
        "packet_loss_rate": 1.71,
        "jitter": 29.027,
        "speed": 16.0
    },
    "QoE": 89.608497,
    "timestamp": 20250406122804
}