{
    "20250403191056": {
        "throughput": 731.8,
        "packets_lost": 2.5,
        "packet_loss_rate": 1.04,
        "jitter": 24.699536456776645,
        "speed": 27.0
    },
    "20250403191058": {
        "throughput": 723.3,
        "packets_lost": 4.9,
        "packet_loss_rate": 0.83,
        "jitter": 25.41836888141006,
        "speed": 25.0
    },
    "20250403191100": {
        "throughput": 813.6,
        "packets_lost": 2.2,
        "packet_loss_rate": 4.6,
        "jitter": 32.284519492817026,
        "speed": 38.0
    },
    "20250403191102": {
        "throughput": 1490.8,
        "packets_lost": 4.6,
        "packet_loss_rate": 4.36,
        "jitter": 32.46080194459942,
        "speed": 7.0
    },
    "20250403191104": {
        "throughput": 1193.3,
        "packets_lost": 3.8,
        "packet_loss_rate": 4.11,
        "jitter": 32.10756354967332,
        "speed": 16.0
    },
    "QoE": 75.9814908,
    "timestamp": 20250403191104
}