{
    "20250403214246": {
        "throughput": 1328.1,
        "packets_lost": 0.2,
        "packet_loss_rate": 4.82,
        "jitter": 17.235,
        "speed": 9.0
    },
    "20250403214248": {
        "throughput": 847.0,
        "packets_lost": 3.2,
        "packet_loss_rate": 1.56,
        "jitter": 26.079,
        "speed": 18.0
    },
    "20250403214250": {
        "throughput": 1534.0,
        "packets_lost": 2.5,
        "packet_loss_rate": 0.28,
        "jitter": 21.571,
        "speed": 36.0
    },
    "20250403214252": {
        "throughput": 1205.3,
        "packets_lost": 1.8,
        "packet_loss_rate": 3.75,
        "jitter": 28.275,
        "speed": 44.0
    },
    "20250403214254": {
        "throughput": 1020.4,
        "packets_lost": 3.2,
        "packet_loss_rate": 2.12,
        "jitter": 27.113,
        "speed": 15.0
    },
    "QoE": 84.22322940000001,
    "timestamp": 20250403214254
}