{
    "20250409211716": {
        "throughput": 821.0,
        "packets_lost": 2.2,
        "packet_loss_rate": 1.86,
        "jitter": 27.433,
        "speed": 19.0
    },
    "20250409211718": {
        "throughput": 1154.6,
        "packets_lost": 3.0,
        "packet_loss_rate": 4.13,
        "jitter": 25.538,
        "speed": 32.0
    },
    "20250409211720": {
        "throughput": 1340.0,
        "packets_lost": 4.3,
        "packet_loss_rate": 1.0,
        "jitter": 17.269,
        "speed": 3.0
    },
    "20250409211722": {
        "throughput": 722.7,
        "packets_lost": 0.8,
        "packet_loss_rate": 2.33,
        "jitter": 29.0,
        "speed": 50.0
    },
    "20250409211724": {
        "throughput": 1154.1,
        "packets_lost": 0.7,
        "packet_loss_rate": 4.71,
        "jitter": 21.835,
        "speed": 34.0
    },
    "QoE": 81.7572898,
    "timestamp": 20250409211724
}