{
    "20250413133616": {
        "throughput": 1434.2,
        "packets_lost": 1.9,
        "packet_loss_rate": 3.56,
        "jitter": 20.751,
        "speed": 27.0
    },
    "20250413133618": {
        "throughput": 718.3,
        "packets_lost": 4.5,
        "packet_loss_rate": 0.78,
        "jitter": 18.365,
        "speed": 33.0
    },
    "20250413133620": {
        "throughput": 612.7,
        "packets_lost": 0.2,
        "packet_loss_rate": 4.51,
        "jitter": 17.597,
        "speed": 50.0
    },
    "20250413133622": {
        "throughput": 1047.5,
        "packets_lost": 4.4,
        "packet_loss_rate": 1.89,
        "jitter": 29.511,
        "speed": 13.0
    },
    "20250413133624": {
        "throughput": 879.9,
        "packets_lost": 0.3,
        "packet_loss_rate": 0.95,
        "jitter": 25.721,
        "speed": 24.0
    },
    "QoE": 83.7725394,
    "timestamp": 20250413133624
}