{
    "20250411065806": {
        "throughput": 1347.8,
        "packets_lost": 2.5,
        "packet_loss_rate": 1.29,
        "jitter": 26.965,
        "speed": 25.0
    },
    "20250411065808": {
        "throughput": 713.3,
        "packets_lost": 1.1,
        "packet_loss_rate": 0.01,
        "jitter": 15.798,
        "speed": 31.0
    },
    "20250411065810": {
        "throughput": 1532.6,
        "packets_lost": 1.3,
        "packet_loss_rate": 4.59,
        "jitter": 15.166,
        "speed": 31.0
    },
    "20250411065812": {
        "throughput": 779.2,
        "packets_lost": 2.9,
        "packet_loss_rate": 0.33,
        "jitter": 29.486,
        "speed": 27.0
    },
    "20250411065814": {
        "throughput": 1082.6,
        "packets_lost": 4.6,
        "packet_loss_rate": 2.51,
        "jitter": 15.838,
        "speed": 3.0
    },
    "QoE": 86.78780880000001,
    "timestamp": 20250411065814
}