{
    "20250411173936": {
        "throughput": 699.5,
        "packets_lost": 1.0,
        "packet_loss_rate": 4.27,
        "jitter": 24.99902290360514,
        "speed": 6.0
    },
    "20250411173938": {
        "throughput": 1549.5,
        "packets_lost": 3.7,
        "packet_loss_rate": 4.04,
        "jitter": 21.83651472150465,
        "speed": 48.0
    },
    "20250411173940": {
        "throughput": 1180.7,
        "packets_lost": 0.4,
        "packet_loss_rate": 2.48,
        "jitter": 22.87964255988058,
        "speed": 59.0
    },
    "20250411173942": {
        "throughput": 1036.8,
        "packets_lost": 4.7,
        "packet_loss_rate": 2.16,
        "jitter": 22.607873456164302,
        "speed": 41.0
    },
    "20250411173944": {
        "throughput": 605.1,
        "packets_lost": 1.4,
        "packet_loss_rate": 3.68,
        "jitter": 26.56876563221965,
        "speed": 56.0
    },
    "QoE": 74.4683994,
    "timestamp": 20250411173944
}