{
    "20250406233746": {
        "throughput": 701.2,
        "packets_lost": 1.7,
        "packet_loss_rate": 3.47,
        "jitter": 19.844,
        "speed": 54.0
    },
    "20250406233748": {
        "throughput": 909.5,
        "packets_lost": 0.9,
        "packet_loss_rate": 4.35,
        "jitter": 16.125,
        "speed": 8.0
    },
    "20250406233750": {
        "throughput": 875.8,
        "packets_lost": 1.3,
        "packet_loss_rate": 1.71,
        "jitter": 16.981,
        "speed": 8.0
    },
    "20250406233752": {
        "throughput": 936.6,
        "packets_lost": 0.3,
        "packet_loss_rate": 1.47,
        "jitter": 22.26,
        "speed": 51.0
    },
    "20250406233754": {
        "throughput": 1498.0,
        "packets_lost": 2.6,
        "packet_loss_rate": 2.06,
        "jitter": 21.035,
        "speed": 21.0
    },
    "QoE": 83.178208,
    "timestamp": 20250406233754
}