{
    "20250413122346": {
        "throughput": 806.5,
        "packets_lost": 0.7,
        "packet_loss_rate": 1.14,
        "jitter": 25.932,
        "speed": 20.0
    },
    "20250413122348": {
        "throughput": 1150.3,
        "packets_lost": 3.7,
        "packet_loss_rate": 3.72,
        "jitter": 16.979,
        "speed": 10.0
    },
    "20250413122350": {
        "throughput": 642.7,
        "packets_lost": 2.7,
        "packet_loss_rate": 4.56,
        "jitter": 29.1,
        "speed": 39.0
    },
    "20250413122352": {
        "throughput": 917.4,
        "packets_lost": 2.2,
        "packet_loss_rate": 0.98,
        "jitter": 23.059,
        "speed": 14.0
    },
    "20250413122354": {
        "throughput": 965.9,
        "packets_lost": 4.1,
        "packet_loss_rate": 2.67,
        "jitter": 18.334,
        "speed": 58.0
    },
    "QoE": 81.9993236,
    "timestamp": 20250413122354
}