{
    "20250412054416": {
        "throughput": 1157.2,
        "packets_lost": 0.7,
        "packet_loss_rate": 2.44,
        "jitter": 15.704,
        "speed": 48.0
    },
    "20250412054418": {
        "throughput": 1535.5,
        "packets_lost": 4.9,
        "packet_loss_rate": 3.34,
        "jitter": 26.792,
        "speed": 24.0
    },
    "20250412054420": {
        "throughput": 1329.5,
        "packets_lost": 1.8,
        "packet_loss_rate": 3.96,
        "jitter": 29.705,
        "speed": 9.0
    },
    "20250412054422": {
        "throughput": 1440.7,
        "packets_lost": 0.3,
        "packet_loss_rate": 2.32,
        "jitter": 27.068,
        "speed": 30.0
    },
    "20250412054424": {
        "throughput": 758.5,
        "packets_lost": 4.0,
        "packet_loss_rate": 4.02,
        "jitter": 21.076,
        "speed": 12.0
    },
    "QoE": 81.4065996,
    "timestamp": 20250412054424
}