{
    "20250405082546": {
        "throughput": 794.2,
        "packets_lost": 0.6,
        "packet_loss_rate": 0.57,
        "jitter": 29.707738414369995,
        "speed": 52.0
    },
    "20250405082548": {
        "throughput": 1492.5,
        "packets_lost": 4.7,
        "packet_loss_rate": 2.29,
        "jitter": 20.64283862403319,
        "speed": 56.0
    },
    "20250405082550": {
        "throughput": 1010.1,
        "packets_lost": 0.7,
        "packet_loss_rate": 0.17,
        "jitter": 19.705290860307617,
        "speed": 13.0
    },
    "20250405082552": {
        "throughput": 1519.0,
        "packets_lost": 2.3,
        "packet_loss_rate": 0.05,
        "jitter": 22.479714574745504,
        "speed": 31.0
    },
    "20250405082554": {
        "throughput": 1577.8,
        "packets_lost": 2.0,
        "packet_loss_rate": 2.59,
        "jitter": 21.686804166091964,
        "speed": 1.0
    },
    "QoE": 85.0619256,
    "timestamp": 20250405082554
}