{
    "20250408164946": {
        "throughput": 1211.2,
        "packets_lost": 3.4,
        "packet_loss_rate": 3.62,
        "jitter": 19.109,
        "speed": 34.0
    },
    "20250408164948": {
        "throughput": 1013.4,
        "packets_lost": 3.1,
        "packet_loss_rate": 3.61,
        "jitter": 16.505,
        "speed": 7.0
    },
    "20250408164950": {
        "throughput": 1361.8,
        "packets_lost": 4.8,
        "packet_loss_rate": 1.65,
        "jitter": 16.583,
        "speed": 16.0
    },
    "20250408164952": {
        "throughput": 842.6,
        "packets_lost": 1.6,
        "packet_loss_rate": 1.33,
        "jitter": 27.628,
        "speed": 35.0
    },
    "20250408164954": {
        "throughput": 1038.2,
        "packets_lost": 3.9,
        "packet_loss_rate": 4.63,
        "jitter": 18.479,
        "speed": 37.0
    },
    "QoE": 81.7605874,
    "timestamp": 20250408164954
}