{
    "20250404194646": {
        "throughput": 915.7,
        "packets_lost": 0.5,
        "packet_loss_rate": 4.31,
        "jitter": 20.075190974771942,
        "speed": 23.0
    },
    "20250404194648": {
        "throughput": 1158.9,
        "packets_lost": 0.8,
        "packet_loss_rate": 3.19,
        "jitter": 24.314403362648005,
        "speed": 59.0
    },
    "20250404194650": {
        "throughput": 891.9,
        "packets_lost": 3.8,
        "packet_loss_rate": 0.68,
        "jitter": 19.69348707812252,
        "speed": 12.0
    },
    "20250404194652": {
        "throughput": 778.8,
        "packets_lost": 0.5,
        "packet_loss_rate": 4.38,
        "jitter": 18.54624525451334,
        "speed": 34.0
    },
    "20250404194654": {
        "throughput": 1000.5,
        "packets_lost": 3.1,
        "packet_loss_rate": 1.92,
        "jitter": 29.460857360431458,
        "speed": 46.0
    },
    "QoE": 76.229859,
    "timestamp": 20250404194654
}