{
    "20250408171846": {
        "throughput": 733.0,
        "packets_lost": 1.7,
        "packet_loss_rate": 3.92,
        "jitter": 21.81927172820427,
        "speed": 39.0
    },
    "20250408171848": {
        "throughput": 1502.3,
        "packets_lost": 1.3,
        "packet_loss_rate": 0.02,
        "jitter": 28.662898025996466,
        "speed": 52.0
    },
    "20250408171850": {
        "throughput": 1121.9,
        "packets_lost": 2.1,
        "packet_loss_rate": 3.3,
        "jitter": 18.03747897213239,
        "speed": 15.0
    },
    "20250408171852": {
        "throughput": 1172.8,
        "packets_lost": 0.4,
        "packet_loss_rate": 0.2,
        "jitter": 29.55345419686164,
        "speed": 12.0
    },
    "20250408171854": {
        "throughput": 1050.6,
        "packets_lost": 1.7,
        "packet_loss_rate": 0.74,
        "jitter": 18.130160111568195,
        "speed": 39.0
    },
    "QoE": 82.35429839999999,
    "timestamp": 20250408171854
}