{
    "20250404220926": {
        "throughput": 854.9,
        "packets_lost": 0.3,
        "packet_loss_rate": 1.97,
        "jitter": 16.949,
        "speed": 27.0
    },
    "20250404220928": {
        "throughput": 1192.1,
        "packets_lost": 4.9,
        "packet_loss_rate": 1.79,
        "jitter": 16.836,
        "speed": 13.0
    },
    "20250404220930": {
        "throughput": 1061.6,
        "packets_lost": 0.5,
        "packet_loss_rate": 2.62,
        "jitter": 24.13,
        "speed": 54.0
    },
    "20250404220932": {
        "throughput": 1032.4,
        "packets_lost": 4.8,
        "packet_loss_rate": 4.82,
        "jitter": 28.007,
        "speed": 28.0
    },
    "20250404220934": {
        "throughput": 939.7,
        "packets_lost": 3.3,
        "packet_loss_rate": 2.53,
        "jitter": 18.092,
        "speed": 40.0
    },
    "QoE": 82.63448480000001,
    "timestamp": 20250404220934
}