{
    "20250406231736": {
        "throughput": 1300.1,
        "packets_lost": 0.7,
        "packet_loss_rate": 1.65,
        "jitter": 29.079,
        "speed": 48.0
    },
    "20250406231738": {
        "throughput": 1145.3,
        "packets_lost": 3.1,
        "packet_loss_rate": 4.31,
        "jitter": 29.315,
        "speed": 39.0
    },
    "20250406231740": {
        "throughput": 1339.4,
        "packets_lost": 4.9,
        "packet_loss_rate": 4.28,
        "jitter": 27.995,
        "speed": 27.0
    },
    "20250406231742": {
        "throughput": 942.7,
        "packets_lost": 3.7,
        "packet_loss_rate": 3.59,
        "jitter": 29.432,
        "speed": 54.0
    },
    "20250406231744": {
        "throughput": 1400.8,
        "packets_lost": 1.6,
        "packet_loss_rate": 4.92,
        "jitter": 28.363,
        "speed": 15.0
    },
    "QoE": 78.2340074,
    "timestamp": 20250406231744
}