{
    "20250404221446": {
        "throughput": 801.6,
        "packets_lost": 3.7,
        "packet_loss_rate": 4.62,
        "jitter": 22.237,
        "speed": 12.0
    },
    "20250404221448": {
        "throughput": 1406.9,
        "packets_lost": 3.7,
        "packet_loss_rate": 2.61,
        "jitter": 22.957,
        "speed": 57.0
    },
    "20250404221450": {
        "throughput": 1476.9,
        "packets_lost": 4.8,
        "packet_loss_rate": 2.89,
        "jitter": 15.262,
        "speed": 19.0
    },
    "20250404221452": {
        "throughput": 1130.9,
        "packets_lost": 0.3,
        "packet_loss_rate": 3.41,
        "jitter": 15.388,
        "speed": 35.0
    },
    "20250404221454": {
        "throughput": 1345.3,
        "packets_lost": 3.5,
        "packet_loss_rate": 3.4,
        "jitter": 24.31,
        "speed": 40.0
    },
    "QoE": 81.2467556,
    "timestamp": 20250404221454
}